minimal_pandas_api_for_polars/__init__.py
minimal_pandas_api_for_polars/lib/__init__.py
minimal_pandas_api_for_polars/lib/helpers/__init__.py
minimal_pandas_api_for_polars/lib/helpers/convert_builtin_python_class_to_polars_dtype.py
minimal_pandas_api_for_polars/lib/helpers/finalize_select_exprs.py
minimal_pandas_api_for_polars/lib/helpers/fqn.py
minimal_pandas_api_for_polars/lib/helpers/get_restcols_select_expr.py
minimal_pandas_api_for_polars/lib/helpers/is_convertible_builtin_python_class.py
minimal_pandas_api_for_polars/lib/helpers/is_polars_dtype_directive.py
minimal_pandas_api_for_polars/lib/helpers/pandas_dtype_directive_to_polars_dtype.py
minimal_pandas_api_for_polars/lib/helpers/polars_dtype_to_pandas_dtype_name.py
minimal_pandas_api_for_polars/lib/helpers/polars_dtype_to_python_primitive_type.py
minimal_pandas_api_for_polars/lib/helpers/testing_utils.py
minimal_pandas_api_for_polars/lib/helpers/to_polars_dtype_directive.py
minimal_pandas_api_for_polars/lib/helpers/types.py
minimal_pandas_api_for_polars/lib/interop/__init__.py
minimal_pandas_api_for_polars/lib/interop/pd_to_pl.py
minimal_pandas_api_for_polars/lib/interop/pl_to_pandas.py
minimal_pandas_api_for_polars/lib/pandas_api/__init__.py
minimal_pandas_api_for_polars/lib/pandas_api/pl_assert_frame_equal.py
minimal_pandas_api_for_polars/lib/pandas_api/pl_assert_series_equal.py
minimal_pandas_api_for_polars/lib/pandas_api/pl_assign.py
minimal_pandas_api_for_polars/lib/pandas_api/pl_astype.py
minimal_pandas_api_for_polars/lib/pandas_api/pl_drop.py
minimal_pandas_api_for_polars/lib/pandas_api/pl_drop_duplicates.py
minimal_pandas_api_for_polars/lib/pandas_api/pl_dropna.py
minimal_pandas_api_for_polars/lib/pandas_api/pl_dtypes.py
minimal_pandas_api_for_polars/lib/pandas_api/pl_info.py
minimal_pandas_api_for_polars/lib/pandas_api/pl_rename.py
minimal_pandas_api_for_polars/lib/pandas_api/pl_select_dtypes.py
minimal_pandas_api_for_polars/lib/pandas_api/pl_sort_values.py
minimal_pandas_api_for_polars-0.1.1.dist-info/WHEEL
minimal_pandas_api_for_polars-0.1.1.dist-info/METADATA
minimal_pandas_api_for_polars-0.1.1.dist-info/RECORD
